modin_spreadsheet/__init__.py
modin_spreadsheet/_version.py
modin_spreadsheet/constants.py
modin_spreadsheet/grid.py
modin_spreadsheet/static/097df1053ff3246e2f1af9d5a858ac6c.gif
modin_spreadsheet/static/0d6de499db574dd313c1f3500d337d1a.png
modin_spreadsheet/static/1e360be5458b462df279dadad6eee0cc.png
modin_spreadsheet/static/7e2ccbc3b7b736251403b238014dcacc.gif
modin_spreadsheet/static/853909d9945e29dd80d5c7d42f9b711e.png
modin_spreadsheet/static/86586a919bd10f4cedba392f64336a54.gif
modin_spreadsheet/static/8fcbe60e4efd8e2d1742bba8486994e1.gif
modin_spreadsheet/static/9a52a923ceb5983fa0943c1e24d6d35b.gif
modin_spreadsheet/static/a4a8691ca395136aee475a56913b3456.png
modin_spreadsheet/static/dc29114100c22b4660e3ec311004c1fd.png
modin_spreadsheet/static/e084661154ad58415fa1a8f54a04c5e9.png
modin_spreadsheet/static/e38f33bbf55d6e20d21c4a10b9912668.gif
modin_spreadsheet/static/extension.js
modin_spreadsheet/static/index.js
modin_spreadsheet/static/index.js.map
modin_spreadsheet/tests/__init__.py
modin_spreadsheet/tests/test_grid.py
modin_spreadsheet-0.1.2.data/data/share/jupyter/nbextensions/modin_spreadsheet/097df1053ff3246e2f1af9d5a858ac6c.gif
modin_spreadsheet-0.1.2.data/data/share/jupyter/nbextensions/modin_spreadsheet/0d6de499db574dd313c1f3500d337d1a.png
modin_spreadsheet-0.1.2.data/data/share/jupyter/nbextensions/modin_spreadsheet/1e360be5458b462df279dadad6eee0cc.png
modin_spreadsheet-0.1.2.data/data/share/jupyter/nbextensions/modin_spreadsheet/7e2ccbc3b7b736251403b238014dcacc.gif
modin_spreadsheet-0.1.2.data/data/share/jupyter/nbextensions/modin_spreadsheet/853909d9945e29dd80d5c7d42f9b711e.png
modin_spreadsheet-0.1.2.data/data/share/jupyter/nbextensions/modin_spreadsheet/86586a919bd10f4cedba392f64336a54.gif
modin_spreadsheet-0.1.2.data/data/share/jupyter/nbextensions/modin_spreadsheet/8fcbe60e4efd8e2d1742bba8486994e1.gif
modin_spreadsheet-0.1.2.data/data/share/jupyter/nbextensions/modin_spreadsheet/9a52a923ceb5983fa0943c1e24d6d35b.gif
modin_spreadsheet-0.1.2.dist-info/LICENSE
modin_spreadsheet-0.1.2.dist-info/METADATA
modin_spreadsheet-0.1.2.dist-info/WHEEL
modin_spreadsheet-0.1.2.dist-info/top_level.txt
modin_spreadsheet-0.1.2.dist-info/RECORD
